MANIFEST.in
README.rst
setup.cfg
setup.py
docs/HISTORY.txt
docs/INSTALL.txt
docs/LICENSE.GPL
docs/LICENSE.txt
seantis/__init__.py
seantis.reservation.egg-info/PKG-INFO
seantis.reservation.egg-info/SOURCES.txt
seantis.reservation.egg-info/dependency_links.txt
seantis.reservation.egg-info/entry_points.txt
seantis.reservation.egg-info/namespace_packages.txt
seantis.reservation.egg-info/not-zip-safe
seantis.reservation.egg-info/requires.txt
seantis.reservation.egg-info/top_level.txt
seantis/reservation/__init__.py
seantis/reservation/allocate.py
seantis/reservation/base.py
seantis/reservation/configure.zcml
seantis/reservation/datagenerator.py
seantis/reservation/error.py
seantis/reservation/events.py
seantis/reservation/export.py
seantis/reservation/exposure.py
seantis/reservation/form.py
seantis/reservation/interfaces.py
seantis/reservation/javascript.py
seantis/reservation/macros.py
seantis/reservation/mail.py
seantis/reservation/mail_templates.py
seantis/reservation/maintenance.py
seantis/reservation/overview.py
seantis/reservation/plone_session.py
seantis/reservation/reservations.py
seantis/reservation/reserve.py
seantis/reservation/resource.py
seantis/reservation/restricted_eval.py
seantis/reservation/search.py
seantis/reservation/session.py
seantis/reservation/settings.py
seantis/reservation/setuphandlers.py
seantis/reservation/sync.sh
seantis/reservation/testing.py
seantis/reservation/throttle.py
seantis/reservation/timeframe.py
seantis/reservation/upgrades.py
seantis/reservation/upgrades.zcml
seantis/reservation/utils.py
seantis/reservation/css/base.css
seantis/reservation/css/jquery.timetable.css
seantis/reservation/css/miniTip.css
seantis/reservation/css/print.css
seantis/reservation/css/izug/overview.css
seantis/reservation/css/izug/report.css
seantis/reservation/css/izug/resource.css
seantis/reservation/css/sunburst/overview.css
seantis/reservation/css/sunburst/report.css
seantis/reservation/css/sunburst/resource.css
seantis/reservation/css/teamraum/overview.css
seantis/reservation/css/teamraum/report.css
seantis/reservation/css/teamraum/resource.css
seantis/reservation/emails/reservation_approved.de.txt
seantis/reservation/emails/reservation_approved.en.txt
seantis/reservation/emails/reservation_denied.de.txt
seantis/reservation/emails/reservation_denied.en.txt
