Metadata-Version: 1.1
Name: seantis.reservation
Version: 1.4.0
Summary: Plone addon to reserve stuff in a calendar.
Home-page: https://github.com/seantis/seantis.reservation
Author: Seantis GmbH
Author-email: info@seantis.ch
License: GPL v2
Keywords: reservation calendar seantis plone dexterity
Platform: UNKNOWN
Classifier: Framework :: Plone
Classifier: Framework :: Plone :: 4.3
Classifier: Intended Audience :: Developers
Classifier: Topic :: Software Development :: Libraries :: Python Modules
Classifier: Programming Language :: Python
